dotfiles/__init__.py
dotfiles/__main__.py
dotfiles/core/__init__.py
dotfiles/core/dry.py
dotfiles/core/logging.py
dotfiles/core/matcher.py
dotfiles/subcommands/__init__.py
dotfiles/subcommands/list/__init__.py
dotfiles/subcommands/sync/__init__.py
dotfiles/subcommands/update/__init__.py
dotfiles_sync-0.0.15.dist-info/LICENSE
dotfiles_sync-0.0.15.dist-info/METADATA
dotfiles_sync-0.0.15.dist-info/WHEEL
dotfiles_sync-0.0.15.dist-info/entry_points.txt
dotfiles_sync-0.0.15.dist-info/top_level.txt
dotfiles_sync-0.0.15.dist-info/RECORD
