Metadata-Version: 2.1
Name: dotfiles-sync
Version: 0.0.15
Summary: Manages dotfile configuration files across operating systems
Home-page: https://github.com/kiran94/dotfiles-sync
License: MIT
Keywords: dotfiles
Platform: UNKNOWN
Requires-Python: >=3.6
Requires-Dist: rich (>=9.5.0)
